{"matchInfo":{"id":"cscy99uqpv172f2igmld7tka","opId":"972968","date":"2018-09-06Z","time":"18:45:00Z","week":"1","lastUpdated":"2018-09-07T12:22:02Z","description":"Germany vs France","sport":{"id":"289u5typ3vp4ifwh5thalohmq","name":"Soccer"},"ruleset":{"id":"79plas4983031idr6vw83nuel","name":"Men"},"competition":{"id":"595nsvo7ykvoe690b1e4u5n56","opId":"941","name":"UEFA Nations League","competitionCode":"NAT","competitionFormat":"International cup","country":{"id":"7yiwjcnhat6jo3f901h266cwl","name":"Europe"}},"tournamentCalendar":{"id":"50fns4q22osy22govjbgow0h6","startDate":"2018-09-06Z","endDate":"2019-06-09Z","name":"2018/2019"},"stage":{"id":"aaietpub8s6j75geglxu3fo16","formatId":"9907on5mu5m92sxo5280lwtii","startDate":"2018-09-06Z","endDate":"2018-11-20Z","name":"League A"},"series":{"id":"d253h7oumr85p36mxyju1wcx6","name":"Group 1"},"contestant":[{"id":"3l2t2db0c5ow2f7s7bhr6mij4","opId":"357","name":"Germany","shortName":"Germany","officialName":"Germany","code":"GER","position":"home","country":{"id":"36min0qztu8eydwvpv8t1is0m","name":"Germany"}},{"id":"4pz87gsel7183b7kcadw1dwzv","opId":"368","name":"France","shortName":"France","officialName":"France","code":"FRA","position":"away","country":{"id":"7gww28djs405rfga69smki84o","name":"France"}}],"venue":{"id":"ck5ov6mmj3vpet5zygnqzri4i","neutral":"no","longName":"Allianz Arena","shortName":"Allianz Arena"}},"liveData":{"matchDetails":{"periodId":14,"matchStatus":"Played","winner":"draw","matchLengthMin":93,"matchLengthSec":10,"period":[{"id":1,"start":"2018-09-06T18:47:23Z","end":"2018-09-06T19:33:29Z","lengthMin":46,"lengthSec":6},{"id":2,"start":"2018-09-06T19:50:41Z","end":"2018-09-06T20:37:45Z","lengthMin":47,"lengthSec":4}],"scores":{"ht":{"home":0,"away":0},"ft":{"home":0,"away":0},"total":{"home":0,"away":0}}},"lineUp":[{"player":[{"playerId":"64pzn3jdqo6y2izlpm8n3tvpx","opPlayerId":"20388","firstName":"Manuel","lastName":"Neuer","matchName":"M. Neuer","shirtNumber":1,"position":"Goalkeeper","positionSide":"Centre","stat":[{"type":"minsPlayed","value":"90"},{"type":"touches","value":"37"},{"type":"expectedGoalsConceded","value":"0.7299"},{"type":"expectedGoalsNonpenaltyConceded","value":"0.7299"},{"type":"expectedGoalsontargetConceded","value":"0.6541"},{"type":"expectedGoalsontargetNonpenaltyConceded","value":"0.6541"},{"type":"expectedAssists","value":"0.00023899"},{"type":"expectedAssistsOpenplay","value":"0.00023899"}]},{"playerId":"6fzbp94hf19ysotdassrqdc5x","opPlayerId":"102380","firstName":"Antonio","lastName":"Rüdiger","matchName":"A. Rüdiger","shirtNumber":16,"position":"Defender","positionSide":"Left","stat":[{"type":"attBxCentre","value":"1"},{"type":"attHdMiss","value":"1"},{"type":"attHdTotal","value":"1"},{"type":"attIboxMiss","value":"1"},{"type":"attMissLeft","value":"1"},{"type":"minsPlayed","value":"90"},{"type":"offtargetAttAssist","value":"2"},{"type":"ontargetAttAssist","value":"1"},{"type":"shotOffTarget","value":"1"},{"type":"totalAttAssist","value":"3"},{"type":"totalScoringAtt","value":"1"},{"type":"touches","value":"75"},{"type":"yellowCard","value":"1"},{"type":"attAssistOpenplay","value":"3"},{"type":"touchesInOppBox","value":"1"},{"type":"expectedGoals","value":"0.052"},{"type":"expectedGoalsNonpenalty","value":"0.052"},{"type":"expectedGoalsSetplay","value":"0.052"},{"type":"expectedGoalsHd","value":"0.052"},{"type":"expectedGoalsConceded","value":"0.7299"},{"type":"expectedGoalsNonpenaltyConceded","value":"0.7299"},{"type":"expectedGoalsontargetConceded","value":"0.6541"},{"type":"expectedGoalsontargetNonpenaltyConceded","value":"0.6541"},{"type":"expectedAssists","value":"0.0404088"},{"type":"expectedAssistsSetplay","value":"3.167e-05"},{"type":"expectedAssistsOpenplay","value":"0.0403771"}]},{"playerId":"cd6i7khi5wgsfsg19c9tcjydx","opPlayerId":"38392","firstName":"Mats","lastName":"Hummels","matchName":"M. Hummels","shirtNumber":5,"position":"Defender","positionSide":"Left/Centre","stat":[{"type":"attBxCentre","value":"1"},{"type":"attFastbreak","value":"1"},{"type":"attHdMiss","value":"1"},{"type":"attHdTarget","value":"1"},{"type":"attHdTotal","value":"2"},{"type":"attIboxMiss","value":"1"},{"type":"attIboxTarget","value":"2"},{"type":"attMissHighLeft","value":"1"},{"type":"attOpenplay","value":"1"},{"type":"attRfTarget","value":"1"},{"type":"attRfTotal","value":"1"},{"type":"attSvHighCentre","value":"1"},{"type":"attSvLowCentre","value":"1"},{"type":"minsPlayed","value":"90"},{"type":"ontargetAttAssist","value":"1"},{"type":"ontargetScoringAtt","value":"2"},{"type":"shotOffTarget","value":"1"},{"type":"totalAttAssist","value":"1"},{"type":"totalScoringAtt","value":"3"},{"type":"touches","value":"98"},{"type":"attAssistOpenplay","value":"1"},{"type":"shotFastbreak","value":"1"},{"type":"touchesInOppBox","value":"4"},{"type":"expectedGoals","value":"0.2276"},{"type":"expectedGoalsNonpenalty","value":"0.2276"},{"type":"expectedGoalsOpenplay","value":"0.1059"},{"type":"expectedGoalsSetplay","value":"0.1217"},{"type":"expectedGoalsHd","value":"0.1217"},{"type":"expectedGoalsRf","value":"0.1059"},{"type":"expectedGoalsConceded","value":"0.7299"},{"type":"expectedGoalsNonpenaltyConceded","value":"0.7299"},{"type":"expectedGoalsontarget","value":"0.0907"},{"type":"expectedGoalsontargetNonpenalty","value":"0.0907"},{"type":"expectedGoalsontargetConceded","value":"0.6541"},{"type":"expectedGoalsontargetNonpenaltyConceded","value":"0.6541"},{"type":"expectedAssists","value":"0.224926"},{"type":"expectedAssistsSetplay","value":"0.00017394"},{"type":"expectedAssistsOpenplay","value":"0.224752"}]},{"playerId":"aftis8f2ahy7dhk5bp8co4q1h","opPlayerId":"40691","firstName":"Jérôme","lastName":"Boateng","matchName":"J. Boateng","shirtNumber":17,"position":"Defender","positionSide":"Centre/Right","stat":[{"type":"minsPlayed","value":"90"},{"type":"ontargetAttAssist","value":"1"},{"type":"totalAttAssist","value":"1"},{"type":"touches","value":"101"},{"type":"attAssistOpenplay","value":"1"},{"type":"expectedGoalsConceded","value":"0.7299"},{"type":"expectedGoalsNonpenaltyConceded","value":"0.7299"},{"type":"expectedGoalsontargetConceded","value":"0.6541"},{"type":"expectedGoalsontargetNonpenaltyConceded","value":"0.6541"},{"type":"expectedAssists","value":"0.016435"},{"type":"expectedAssistsSetplay","value":"0.00017012"},{"type":"expectedAssistsOpenplay","value":"0.0162648"}]},{"playerId":"84mp3eqt1ckw107hwxpby9cd1","opPlayerId":"111251","firstName":"Matthias","lastName":"Ginter","matchName":"M. Ginter","shirtNumber":4,"position":"Defender","positionSide":"Right","stat":[{"type":"attBxCentre","value":"1"},{"type":"attHdTarget","value":"1"},{"type":"attHdTotal","value":"1"},{"type":"attIboxTarget","value":"1"},{"type":"attSvLowLeft","value":"1"},{"type":"minsPlayed","value":"90"},{"type":"ontargetAttAssist","value":"1"},{"type":"ontargetScoringAtt","value":"1"},{"type":"totalAttAssist","value":"1"},{"type":"totalScoringAtt","value":"1"},{"type":"touches","value":"96"},{"type":"attAssistOpenplay","value":"1"},{"type":"touchesInOppBox","value":"1"},{"type":"expectedGoals","value":"0.0712"},{"type":"expectedGoalsNonpenalty","value":"0.0712"},{"type":"expectedGoalsSetplay","value":"0.0712"},{"type":"expectedGoalsHd","value":"0.0712"},{"type":"expectedGoalsConceded","value":"0.7299"},{"type":"expectedGoalsNonpenaltyConceded","value":"0.7299"},{"type":"expectedGoalsontarget","value":"0.1577"},{"type":"expectedGoalsontargetNonpenalty","value":"0.1577"},{"type":"expectedGoalsontargetConceded","value":"0.6541"},{"type":"expectedGoalsontargetNonpenaltyConceded","value":"0.6541"},{"type":"expectedAssists","value":"0.0549866"},{"type":"expectedAssistsSetplay","value":"0.0004372"},{"type":"expectedAssistsOpenplay","value":"0.0545494"}]},{"playerId":"cdcbi6xmy0uts703489e0acb9","opPlayerId":"44989","firstName":"Toni","lastName":"Kroos","matchName":"T. Kroos","shirtNumber":8,"position":"Defensive Midfielder","positionSide":"Left/Centre","stat":[{"type":"minsPlayed","value":"90"},{"type":"offtargetAttAssist","value":"1"},{"type":"ontargetAttAssist","value":"2"},{"type":"totalAttAssist","value":"3"},{"type":"touches","value":"111"},{"type":"attAssistSetplay","value":"3"},{"type":"touchesInOppBox","value":"1"},{"type":"expectedGoalsConceded","value":"0.7299"},{"type":"expectedGoalsNonpenaltyConceded","value":"0.7299"},{"type":"expectedGoalsontargetConceded","value":"0.6541"},{"type":"expectedGoalsontargetNonpenaltyConceded","value":"0.6541"},{"type":"expectedAssists","value":"0.254182"},{"type":"expectedAssistsSetplay","value":"0.19829"},{"type":"expectedAssistsOpenplay","value":"0.0558927"}]},{"playerId":"97nv3y9z2ajz6b4ynoo0jn3kl","opPlayerId":"165687","firstName":"Joshua","lastName":"Kimmich","matchName":"J. Kimmich","shirtNumber":18,"position":"Defensive Midfielder","positionSide":"Centre/Right","stat":[{"type":"attObxCentre","value":"1"},{"type":"attMissHigh","value":"1"},{"type":"attOboxMiss","value":"1"},{"type":"attOpenplay","value":"1"},{"type":"attRfTotal","value":"1"},{"type":"minsPlayed","value":"90"},{"type":"shotOffTarget","value":"1"},{"type":"totalScoringAtt","value":"1"},{"type":"touches","value":"100"},{"type":"touchesInOppBox","value":"1"},{"type":"expectedGoals","value":"0.0256"},{"type":"expectedGoalsNonpenalty","value":"0.0256"},{"type":"expectedGoalsOpenplay","value":"0.0256"},{"type":"expectedGoalsRf","value":"0.0256"},{"type":"expectedGoalsConceded","value":"0.7299"},{"type":"expectedGoalsNonpenaltyConceded","value":"0.7299"},{"type":"expectedGoalsontargetConceded","value":"0.6541"},{"type":"expectedGoalsontargetNonpenaltyConceded","value":"0.6541"},{"type":"expectedAssists","value":"0.0348735"},{"type":"expectedAssistsSetplay","value":"0.00016947"},{"type":"expectedAssistsOpenplay","value":"0.034704"}]},{"playerId":"2pjr6yz65f4uqvwniy4vphn85","opPlayerId":"165153","firstName":"Timo","lastName":"Werner","matchName":"T. Werner","shirtNumber":9,"position":"Attacking Midfielder","positionSide":"Left/Centre","stat":[{"type":"attIboxTarget","value":"1"},{"type":"attOpenplay","value":"1"},{"type":"attRfTarget","value":"1"},{"type":"attRfTotal","value":"1"},{"type":"attSvLowCentre","value":"1"},{"type":"minsPlayed","value":"90"},{"type":"ontargetScoringAtt","value":"1"},{"type":"totalScoringAtt","value":"1"},{"type":"touches","value":"50"},{"type":"touchesInOppBox","value":"5"},{"type":"expectedGoals","value":"0.0414"},{"type":"expectedGoalsNonpenalty","value":"0.0414"},{"type":"expectedGoalsOpenplay","value":"0.0414"},{"type":"expectedGoalsRf","value":"0.0414"},{"type":"expectedGoalsConceded","value":"0.7299"},{"type":"expectedGoalsNonpenaltyConceded","value":"0.7299"},{"type":"expectedGoalsontarget","value":"0.0248"},{"type":"expectedGoalsontargetNonpenalty","value":"0.0248"},{"type":"expectedGoalsontargetConceded","value":"0.6541"},{"type":"expectedGoalsontargetNonpenaltyConceded","value":"0.6541"},{"type":"expectedAssists","value":"0.0874427"},{"type":"expectedAssistsSetplay","value":"0.00099079"},{"type":"expectedAssistsOpenplay","value":"0.0864519"}]},{"playerId":"4w4ldzomkj7fhrc51iimz8no5","opPlayerId":"119090","firstName":"Leon","lastName":"Goretzka","matchName":"L. Goretzka","shirtNumber":6,"position":"Attacking Midfielder","positionSide":"Centre","stat":[{"type":"minsPlayed","value":"66"},{"type":"totalSubOff","value":"1"},{"type":"touches","value":"26"},{"type":"expectedGoalsConceded","value":"0.5637"},{"type":"expectedGoalsNonpenaltyConceded","value":"0.5637"},{"type":"expectedGoalsontargetConceded","value":"0.6541"},{"type":"expectedGoalsontargetNonpenaltyConceded","value":"0.6541"},{"type":"expectedAssists","value":"0.0279751"},{"type":"expectedAssistsOpenplay","value":"0.0279751"}]},{"playerId":"4fq74wp7xzwm214veuxqpdz9x","opPlayerId":"55634","firstName":"Thomas","lastName":"Müller","matchName":"T. Müller","shirtNumber":13,"position":"Attacking Midfielder","positionSide":"Centre/Right","stat":[{"type":"attBxCentre","value":"2"},{"type":"attObxCentre","value":"1"},{"type":"attFastbreak","value":"2"},{"type":"attIboxBlocked","value":"1"},{"type":"attIboxMiss","value":"1"},{"type":"attMissHighRight","value":"1"},{"type":"attOboxTarget","value":"1"},{"type":"attOpenplay","value":"3"},{"type":"attRfTarget","value":"1"},{"type":"attRfTotal","value":"3"},{"type":"attSvLowLeft","value":"1"},{"type":"blockedScoringAtt","value":"1"},{"type":"minsPlayed","value":"90"},{"type":"offtargetAttAssist","value":"1"},{"type":"ontargetScoringAtt","value":"1"},{"type":"shotOffTarget","value":"1"},{"type":"totalAttAssist","value":"1"},{"type":"totalScoringAtt","value":"3"},{"type":"touches","value":"67"},{"type":"attAssistOpenplay","value":"1"},{"type":"shotFastbreak","value":"2"},{"type":"touchesInOppBox","value":"6"},{"type":"expectedGoals","value":"0.3129"},{"type":"expectedGoalsNonpenalty","value":"0.3129"},{"type":"expectedGoalsOpenplay","value":"0.3129"},{"type":"expectedGoalsRf","value":"0.3129"},{"type":"expectedGoalsConceded","value":"0.7299"},{"type":"expectedGoalsNonpenaltyConceded","value":"0.7299"},{"type":"expectedGoalsontarget","value":"0.1724"},{"type":"expectedGoalsontargetNonpenalty","value":"0.1724"},{"type":"expectedGoalsontargetConceded","value":"0.6541"},{"type":"expectedGoalsontargetNonpenaltyConceded","value":"0.6541"},{"type":"expectedAssists","value":"0.0221178"},{"type":"expectedAssistsSetplay","value":"7.151e-05"},{"type":"expectedAssistsOpenplay","value":"0.0220463"}]},{"playerId":"btzfq6521zl3q5uqus8ltov6d","opPlayerId":"50523","firstName":"Marco","lastName":"Reus","matchName":"M. Reus","shirtNumber":11,"position":"Striker","positionSide":"Centre","stat":[{"type":"attBxCentre","value":"1"},{"type":"attIboxTarget","value":"1"},{"type":"attOpenplay","value":"1"},{"type":"attRfTarget","value":"1"},{"type":"attRfTotal","value":"1"},{"type":"attSvHighLeft","value":"1"},{"type":"minsPlayed","value":"83"},{"type":"ontargetScoringAtt","value":"1"},{"type":"totalScoringAtt","value":"1"},{"type":"totalSubOff","value":"1"},{"type":"touches","value":"30"},{"type":"touchesInOppBox","value":"4"},{"type":"expectedGoals","value":"0.0589"},{"type":"expectedGoalsNonpenalty","value":"0.0589"},{"type":"expectedGoalsOpenplay","value":"0.0589"},{"type":"expectedGoalsRf","value":"0.0589"},{"type":"expectedGoalsConceded","value":"0.7"},{"type":"expectedGoalsNonpenaltyConceded","value":"0.7"},{"type":"expectedGoalsontarget","value":"0.1379"},{"type":"expectedGoalsontargetNonpenalty","value":"0.1379"},{"type":"expectedGoalsontargetConceded","value":"0.6541"},{"type":"expectedGoalsontargetNonpenaltyConceded","value":"0.6541"},{"type":"expectedAssists","value":"0.0152435"},{"type":"expectedAssistsOpenplay","value":"0.0152435"}]},{"playerId":"f4qcgzveslklfi8601tep77x1","opPlayerId":"177591","firstName":"Julian","lastName":"Brandt","matchName":"J. Brandt","shirtNumber":10,"position":"Substitute","stat":[]},{"playerId":"36fznb9hzqvn6lnlla7f3ycwl","opPlayerId":"92985","firstName":"Julian","lastName":"Draxler","matchName":"J. Draxler","shirtNumber":7,"position":"Substitute","stat":[]},{"playerId":"9wbf00lybk9fqablaqwg5cn2t","opPlayerId":"59859","firstName":"İlkay","lastName":"Gündoğan","matchName":"İ. Gündoğan","shirtNumber":21,"position":"Substitute","stat":[{"type":"attBxCentre","value":"1"},{"type":"attObxCentre","value":"1"},{"type":"attIboxBlocked","value":"1"},{"type":"attLfTotal","value":"1"},{"type":"attMissHighRight","value":"1"},{"type":"attOboxMiss","value":"1"},{"type":"attOpenplay","value":"2"},{"type":"attRfTotal","value":"1"},{"type":"blockedScoringAtt","value":"1"},{"type":"minsPlayed","value":"24"},{"type":"shotOffTarget","value":"1"},{"type":"totalScoringAtt","value":"2"},{"type":"totalSubOn","value":"1"},{"type":"touches","value":"30"},{"type":"touchesInOppBox","value":"1"},{"type":"expectedGoals","value":"0.103"},{"type":"expectedGoalsNonpenalty","value":"0.103"},{"type":"expectedGoalsOpenplay","value":"0.103"},{"type":"expectedGoalsLf","value":"0.0694"},{"type":"expectedGoalsRf","value":"0.0336"},{"type":"expectedGoalsConceded","value":"0.1662"},{"type":"expectedGoalsNonpenaltyConceded","value":"0.1662"},{"type":"expectedAssists","value":"0.0104834"},{"type":"expectedAssistsOpenplay","value":"0.0104834"}]},{"playerId":"ed20ebhqi5c32vbbsze8r6yuh","opPlayerId":"219847","firstName":"Kai","lastName":"Havertz","matchName":"K. Havertz","shirtNumber":20,"position":"Substitute","stat":[]},{"playerId":"cm0gwoyh5rdb216fx685a7l5h","opPlayerId":"201057","firstName":"Thilo","lastName":"Kehrer","matchName":"T. Kehrer","shirtNumber":3,"position":"Substitute","stat":[]},{"playerId":"3w8uk04gxlm4tj4hmsc3msmvp","opPlayerId":"40689","firstName":"Nils","lastName":"Petersen","matchName":"N. Petersen","shirtNumber":23,"position":"Substitute","stat":[]},{"playerId":"4603xrdk721lqhd1ejn62x5n9","opPlayerId":"182156","firstName":"Leroy","lastName":"Sané","matchName":"L. Sané","shirtNumber":19,"position":"Substitute","stat":[{"type":"minsPlayed","value":"7"},{"type":"totalSubOn","value":"1"},{"type":"touches","value":"6"},{"type":"expectedGoalsConceded","value":"0.0299"},{"type":"expectedGoalsNonpenaltyConceded","value":"0.0299"},{"type":"expectedAssists","value":"0.00107725"},{"type":"expectedAssistsOpenplay","value":"0.00107725"}]},{"playerId":"dj85zn6tc073f7egxlfx7793p","opPlayerId":"85073","firstName":"Nico","lastName":"Schulz","matchName":"N. Schulz","shirtNumber":14,"position":"Substitute","stat":[]},{"playerId":"4vy3j1o829f561jf4fqum7ob9","opPlayerId":"161450","firstName":"Niklas","lastName":"Süle","matchName":"N. Süle","shirtNumber":15,"position":"Substitute","stat":[]},{"playerId":"5ec2ede9uwbft3wby33mwowyd","opPlayerId":"164454","firstName":"Jonathan","lastName":"Tah","matchName":"J. Tah","shirtNumber":2,"position":"Substitute","stat":[]},{"playerId":"2e55g4q93y382cg7h0yk5rtud","opPlayerId":"77318","firstName":"Marc-André","lastName":"ter Stegen","matchName":"M. ter Stegen","shirtNumber":22,"position":"Substitute","stat":[]}],"stat":[{"fh":"1","sh":"6","type":"attBxCentre","value":"7"},{"fh":"0","sh":"3","type":"attObxCentre","value":"3"},{"fh":"0","sh":"3","type":"attFastbreak","value":"3"},{"fh":"2","sh":"0","type":"attHdMiss","value":"2"},{"fh":"0","sh":"2","type":"attHdTarget","value":"2"},{"fh":"2","sh":"2","type":"attHdTotal","value":"4"},{"fh":"0","sh":"2","type":"attIboxBlocked","value":"2"},{"fh":"2","sh":"1","type":"attIboxMiss","value":"3"},{"fh":"1","sh":"4","type":"attIboxTarget","value":"5"},{"fh":"0","sh":"1","type":"attLfTotal","value":"1"},{"fh":"0","sh":"1","type":"attMissHigh","value":"1"},{"fh":"1","sh":"0","type":"attMissHighLeft","value":"1"},{"fh":"0","sh":"2","type":"attMissHighRight","value":"2"},{"fh":"1","sh":"0","type":"attMissLeft","value":"1"},{"fh":"0","sh":"2","type":"attOboxMiss","value":"2"},{"fh":"0","sh":"1","type":"attOboxTarget","value":"1"},{"fh":"1","sh":"8","type":"attOpenplay","value":"9"},{"fh":"1","sh":"3","type":"attRfTarget","value":"4"},{"fh":"1","sh":"7","type":"attRfTotal","value":"8"},{"fh":"0","sh":"1","type":"attSvHighCentre","value":"1"},{"fh":"0","sh":"1","type":"attSvHighLeft","value":"1"},{"fh":"1","sh":"1","type":"attSvLowCentre","value":"2"},{"fh":"0","sh":"2","type":"attSvLowLeft","value":"2"},{"fh":"0","sh":"2","type":"blockedScoringAtt","value":"2"},{"fh":"2","sh":"2","type":"offtargetAttAssist","value":"4"},{"fh":"1","sh":"5","type":"ontargetAttAssist","value":"6"},{"fh":"1","sh":"5","type":"ontargetScoringAtt","value":"6"},{"fh":"2","sh":"3","type":"shotOffTarget","value":"5"},{"fh":"0","sh":"2","type":"subsMade","value":"2"},{"fh":"3","sh":"7","type":"totalAttAssist","value":"10"},{"fh":"3","sh":"10","type":"totalScoringAtt","value":"13"},{"fh":"0","sh":"1","type":"totalYellowCard","value":"1"},{"fh":"374","sh":"453","type":"touches","value":"827"},{"fh":"2","sh":"5","type":"attAssistOpenplay","value":"7"},{"fh":"1","sh":"2","type":"attAssistSetplay","value":"3"},{"fh":"0","sh":"3","type":"shotFastbreak","value":"3"},{"fh":"9","sh":"15","type":"touchesInOppBox","value":"24"},{"fh":"0.1467","sh":"0.697364","type":"expectedGoals","value":"0.844064"},{"fh":"0.1467","sh":"0.697364","type":"expectedGoalsNonpenalty","value":"0.844064"},{"fh":"0.0414","sh":"0.557764","type":"expectedGoalsOpenplay","value":"0.599164"},{"fh":"0.1053","sh":"0.1396","type":"expectedGoalsSetplay","value":"0.2449"},{"fh":"0.1053","sh":"0.1396","type":"expectedGoalsHd","value":"0.2449"},{"fh":"0","sh":"0.0694","type":"expectedGoalsLf","value":"0.0694"},{"fh":"0.0414","sh":"0.5369","type":"expectedGoalsRf","value":"0.5783"},{"fh":"0.4864","sh":"0.2435","type":"expectedGoalsConceded","value":"0.7299"},{"fh":"0.4864","sh":"0.2435","type":"expectedGoalsNonpenaltyConceded","value":"0.7299"},{"fh":"0.0248","sh":"0.5587","type":"expectedGoalsontarget","value":"0.5835"},{"fh":"0.0248","sh":"0.5587","type":"expectedGoalsontargetNonpenalty","value":"0.5835"},{"fh":"0.5263","sh":"0.1278","type":"expectedGoalsontargetConceded","value":"0.6541"},{"fh":"0.5263","sh":"0.1278","type":"expectedGoalsontargetNonpenaltyConceded","value":"0.6541"},{"fh":"0.132903","sh":"0.657487","type":"expectedAssists","value":"0.790391"},{"fh":"0.027629","sh":"0.172705","type":"expectedAssistsSetplay","value":"0.200334"},{"fh":"0.105274","sh":"0.484782","type":"expectedAssistsOpenplay","value":"0.590056"}],"contestantId":"3l2t2db0c5ow2f7s7bhr6mij4","opContestantId":"357","teamOfficial":{"id":"90n4dp1aqhtsbpa11h2mz7lqt","opId":"969","firstName":"Joachim","lastName":"Löw","type":"manager"}},{"player":[{"playerId":"9eaevg9okpy4gcm6yofg7vbv9","opPlayerId":"84182","firstName":"Alphonse","lastName":"Areola","matchName":"A. Areola","shirtNumber":16,"position":"Goalkeeper","positionSide":"Centre","stat":[{"type":"minsPlayed","value":"90"},{"type":"touches","value":"45"},{"type":"expectedGoalsConceded","value":"0.844064"},{"type":"expectedGoalsNonpenaltyConceded","value":"0.844064"},{"type":"expectedGoalsontargetConceded","value":"0.5835"},{"type":"expectedGoalsontargetNonpenaltyConceded","value":"0.5835"},{"type":"expectedAssists","value":"0.00143055"},{"type":"expectedAssistsSetplay","value":"8.28e-05"},{"type":"expectedAssistsOpenplay","value":"0.00134775"}]},{"playerId":"c80tzy7t4hoa8fpbek1od4lw5","opPlayerId":"174888","firstName":"Lucas","lastName":"Hernández Pi","matchName":"L. Hernández","shirtNumber":21,"position":"Defender","positionSide":"Left","stat":[{"type":"minsPlayed","value":"90"},{"type":"touches","value":"49"},{"type":"expectedGoalsConceded","value":"0.844064"},{"type":"expectedGoalsNonpenaltyConceded","value":"0.844064"},{"type":"expectedGoalsontargetConceded","value":"0.5835"},{"type":"expectedGoalsontargetNonpenaltyConceded","value":"0.5835"},{"type":"expectedAssists","value":"0.0117767"},{"type":"expectedAssistsSetplay","value":"0.00099104"},{"type":"expectedAssistsOpenplay","value":"0.0107857"}]},{"playerId":"8mlps3xgwbxa7svajxfk2exud","opPlayerId":"88580","firstName":"Samuel Yves","lastName":"Umtiti","matchName":"S. Umtiti","shirtNumber":5,"position":"Defender","positionSide":"Left/Centre","stat":[{"type":"minsPlayed","value":"90"},{"type":"touches","value":"58"},{"type":"expectedGoalsConceded","value":"0.844064"},{"type":"expectedGoalsNonpenaltyConceded","value":"0.844064"},{"type":"expectedGoalsontargetConceded","value":"0.5835"},{"type":"expectedGoalsontargetNonpenaltyConceded","value":"0.5835"},{"type":"expectedAssists","value":"0.00100707"},{"type":"expectedAssistsSetplay","value":"4.875e-05"},{"type":"expectedAssistsOpenplay","value":"0.00095832"}]},{"playerId":"3dph74ixutmbpscaon0b25sl","opPlayerId":"90152","firstName":"Raphaël","lastName":"Varane","matchName":"R. Varane","shirtNumber":4,"position":"Defender","positionSide":"Centre/Right","stat":[{"type":"minsPlayed","value":"90"},{"type":"touches","value":"62"},{"type":"expectedGoalsConceded","value":"0.844064"},{"type":"expectedGoalsNonpenaltyConceded","value":"0.844064"},{"type":"expectedGoalsontargetConceded","value":"0.5835"},{"type":"expectedGoalsontargetNonpenaltyConceded","value":"0.5835"},{"type":"expectedAssists","value":"0.00577915"},{"type":"expectedAssistsSetplay","value":"8.45e-06"},{"type":"expectedAssistsOpenplay","value":"0.0057707"}]},{"playerId":"yq0cm7vwr0tkv7nvt9vo77bp","opPlayerId":"202675","firstName":"Benjamin","lastName":"Pavard","matchName":"B. Pavard","shirtNumber":2,"position":"Defender","positionSide":"Right","stat":[{"type":"minsPlayed","value":"90"},{"type":"ontargetAttAssist","value":"1"},{"type":"totalAttAssist","value":"1"},{"type":"touches","value":"65"},{"type":"attAssistOpenplay","value":"1"},{"type":"touchesInOppBox","value":"1"},{"type":"expectedGoalsConceded","value":"0.844064"},{"type":"expectedGoalsNonpenaltyConceded","value":"0.844064"},{"type":"expectedGoalsontargetConceded","value":"0.5835"},{"type":"expectedGoalsontargetNonpenaltyConceded","value":"0.5835"},{"type":"expectedAssists","value":"0.078995"},{"type":"expectedAssistsSetplay","value":"0.00067144"},{"type":"expectedAssistsOpenplay","value":"0.0783236"}]},{"playerId":"am70epdl0361z5af8ahskcdsl","opPlayerId":"116594","firstName":"N'Golo","lastName":"Kanté","matchName":"N. Kanté","shirtNumber":13,"position":"Defensive Midfielder","positionSide":"Left/Centre","stat":[{"type":"minsPlayed","value":"90"},{"type":"ontargetAttAssist","value":"1"},{"type":"totalAttAssist","value":"1"},{"type":"touches","value":"86"},{"type":"attAssistOpenplay","value":"1"},{"type":"expectedGoalsConceded","value":"0.844064"},{"type":"expectedGoalsNonpenaltyConceded","value":"0.844064"},{"type":"expectedGoalsontargetConceded","value":"0.5835"},{"type":"expectedGoalsontargetNonpenaltyConceded","value":"0.5835"},{"type":"expectedAssists","value":"0.0551442"},{"type":"expectedAssistsSetplay","value":"1.669e-05"},{"type":"expectedAssistsOpenplay","value":"0.0551275"}]},{"playerId":"f482w50k80zbyb2ykh84yijf9","opPlayerId":"74208","firstName":"Paul","lastName":"Pogba","matchName":"P. Pogba","shirtNumber":6,"position":"Defensive Midfielder","positionSide":"Centre/Right","stat":[{"type":"attBxCentre","value":"1"},{"type":"attHdMiss","value":"1"},{"type":"attHdTotal","value":"1"},{"type":"attIboxMiss","value":"1"},{"type":"attMissRight","value":"1"},{"type":"minsPlayed","value":"90"},{"type":"shotOffTarget","value":"1"},{"type":"totalScoringAtt","value":"1"},{"type":"touches","value":"58"},{"type":"touchesInOppBox","value":"2"},{"type":"expectedGoals","value":"0.0765"},{"type":"expectedGoalsNonpenalty","value":"0.0765"},{"type":"expectedGoalsSetplay","value":"0.0765"},{"type":"expectedGoalsHd","value":"0.0765"},{"type":"expectedGoalsConceded","value":"0.844064"},{"type":"expectedGoalsNonpenaltyConceded","value":"0.844064"},{"type":"expectedGoalsontargetConceded","value":"0.5835"},{"type":"expectedGoalsontargetNonpenaltyConceded","value":"0.5835"},{"type":"expectedAssists","value":"0.0312773"},{"type":"expectedAssistsSetplay","value":"0.00014734"},{"type":"expectedAssistsOpenplay","value":"0.03113"}]},{"playerId":"e1c4h0keh53jv6fcdtvjv5o7p","opPlayerId":"37971","firstName":"Blaise","lastName":"Matuidi","matchName":"B. Matuidi","shirtNumber":14,"position":"Attacking Midfielder","positionSide":"Left/Centre","stat":[{"type":"minsPlayed","value":"86"},{"type":"totalSubOff","value":"1"},{"type":"touches","value":"34"},{"type":"expectedGoalsConceded","value":"0.844064"},{"type":"expectedGoalsNonpenaltyConceded","value":"0.844064"},{"type":"expectedGoalsontargetConceded","value":"0.5835"},{"type":"expectedGoalsontargetNonpenaltyConceded","value":"0.5835"},{"type":"expectedAssists","value":"0.015754"},{"type":"expectedAssistsSetplay","value":"0.00013053"},{"type":"expectedAssistsOpenplay","value":"0.0156234"}]},{"playerId":"716n1970vi9rvw5b4w9qmjfth","opPlayerId":"76650","firstName":"Antoine","lastName":"Griezmann","matchName":"A. Griezmann","shirtNumber":7,"position":"Attacking Midfielder","positionSide":"Centre","stat":[{"type":"attObxCentre","value":"1"},{"type":"attIboxTarget","value":"1"},{"type":"attLfTarget","value":"2"},{"type":"attLfTotal","value":"2"},{"type":"attOboxTarget","value":"1"},{"type":"attOpenplay","value":"2"},{"type":"attSvLowRight","value":"2"},{"type":"minsPlayed","value":"80"},{"type":"offtargetAttAssist","value":"1"},{"type":"ontargetScoringAtt","value":"2"},{"type":"totalAttAssist","value":"1"},{"type":"totalScoringAtt","value":"2"},{"type":"totalSubOff","value":"1"},{"type":"touches","value":"46"},{"type":"attAssistOpenplay","value":"1"},{"type":"touchesInOppBox","value":"1"},{"type":"expectedGoals","value":"0.0773"},{"type":"expectedGoalsNonpenalty","value":"0.0773"},{"type":"expectedGoalsOpenplay","value":"0.0773"},{"type":"expectedGoalsLf","value":"0.0773"},{"type":"expectedGoalsConceded","value":"0.844064"},{"type":"expectedGoalsNonpenaltyConceded","value":"0.844064"},{"type":"expectedGoalsontarget","value":"0.1278"},{"type":"expectedGoalsontargetNonpenalty","value":"0.1278"},{"type":"expectedGoalsontargetConceded","value":"0.5835"},{"type":"expectedGoalsontargetNonpenaltyConceded","value":"0.5835"},{"type":"expectedAssists","value":"0.0577965"},{"type":"expectedAssistsSetplay","value":"0.00029186"},{"type":"expectedAssistsOpenplay","value":"0.0575047"}]},{"playerId":"5e9ilgrz3tzg9kd1gk3yvrahh","opPlayerId":"220160","firstName":"Kylian","lastName":"Mbappé Lottin","matchName":"K. Mbappé","shirtNumber":10,"position":"Attacking Midfielder","positionSide":"Centre/Right","stat":[{"type":"attObxCentre","value":"2"},{"type":"attFastbreak","value":"1"},{"type":"attFreekickTarget","value":"1"},{"type":"attFreekickTotal","value":"1"},{"type":"attMissLeft","value":"1"},{"type":"attOboxMiss","value":"1"},{"type":"attOboxTarget","value":"1"},{"type":"attOpenplay","value":"1"},{"type":"attRfTarget","value":"1"},{"type":"attRfTotal","value":"2"},{"type":"attSvHighLeft","value":"1"},{"type":"minsPlayed","value":"90"},{"type":"offtargetAttAssist","value":"2"},{"type":"ontargetAttAssist","value":"1"},{"type":"ontargetScoringAtt","value":"1"},{"type":"shotOffTarget","value":"1"},{"type":"totalAttAssist","value":"3"},{"type":"totalScoringAtt","value":"2"},{"type":"touches","value":"42"},{"type":"attAssistOpenplay","value":"2"},{"type":"attAssistSetplay","value":"1"},{"type":"shotFastbreak","value":"1"},{"type":"touchesInOppBox","value":"2"},{"type":"expectedGoals","value":"0.1105"},{"type":"expectedGoalsNonpenalty","value":"0.1105"},{"type":"expectedGoalsOpenplay","value":"0.0598"},{"type":"expectedGoalsSetplay","value":"0.0507"},{"type":"expectedGoalsRf","value":"0.1105"},{"type":"expectedGoalsFreekick","value":"0.0507"},{"type":"expectedGoalsConceded","value":"0.844064"},{"type":"expectedGoalsNonpenaltyConceded","value":"0.844064"},{"type":"expectedGoalsontarget","value":"0.2624"},{"type":"expectedGoalsontargetNonpenalty","value":"0.2624"},{"type":"expectedGoalsontargetFreekick","value":"0.2624"},{"type":"expectedGoalsontargetConceded","value":"0.5835"},{"type":"expectedGoalsontargetNonpenaltyConceded","value":"0.5835"},{"type":"expectedAssists","value":"0.609985"},{"type":"expectedAssistsSetplay","value":"0.0590549"},{"type":"expectedAssistsOpenplay","value":"0.55093"}]},{"playerId":"5awkzgwwh48prwgvxwewuc5hx","opPlayerId":"44346","firstName":"Olivier","lastName":"Giroud","matchName":"O. Giroud","shirtNumber":9,"position":"Striker","positionSide":"Centre","stat":[{"type":"attBxCentre","value":"1"},{"type":"attHdTarget","value":"1"},{"type":"attHdTotal","value":"1"},{"type":"attIboxMiss","value":"1"},{"type":"attIboxTarget","value":"1"},{"type":"attMissLeft","value":"1"},{"type":"attOpenplay","value":"2"},{"type":"attRfTotal","value":"1"},{"type":"attSvLowRight","value":"1"},{"type":"minsPlayed","value":"66"},{"type":"ontargetScoringAtt","value":"1"},{"type":"shotOffTarget","value":"1"},{"type":"totalScoringAtt","value":"2"},{"type":"totalSubOff","value":"1"},{"type":"touches","value":"22"},{"type":"touchesInOppBox","value":"2"},{"type":"expectedGoals","value":"0.4357"},{"type":"expectedGoalsNonpenalty","value":"0.4357"},{"type":"expectedGoalsOpenplay","value":"0.4357"},{"type":"expectedGoalsHd","value":"0.0543"},{"type":"expectedGoalsRf","value":"0.3814"},{"type":"expectedGoalsConceded","value":"0.2582"},{"type":"expectedGoalsNonpenaltyConceded","value":"0.2582"},{"type":"expectedGoalsontarget","value":"0.2639"},{"type":"expectedGoalsontargetNonpenalty","value":"0.2639"},{"type":"expectedGoalsontargetConceded","value":"0.3351"},{"type":"expectedGoalsontargetNonpenaltyConceded","value":"0.3351"},{"type":"expectedAssists","value":"0.00328226"},{"type":"expectedAssistsOpenplay","value":"0.00328226"}]},{"playerId":"2t05pfvho7i9w9w01zcz3gz4l","opPlayerId":"42713","firstName":"Benoît","lastName":"Costil","matchName":"B. Costil","shirtNumber":23,"position":"Substitute","stat":[]},{"playerId":"ckaqxlw257qzj8vjdumvwbaad","opPlayerId":"219438","firstName":"Ousmane","lastName":"Dembélé","matchName":"O. Dembélé","shirtNumber":11,"position":"Substitute","stat":[{"type":"attObxCentre","value":"1"},{"type":"attLfTotal","value":"1"},{"type":"attOboxBlocked","value":"1"},{"type":"attOpenplay","value":"1"},{"type":"blockedScoringAtt","value":"1"},{"type":"minsPlayed","value":"24"},{"type":"totalScoringAtt","value":"1"},{"type":"totalSubOn","value":"1"},{"type":"touches","value":"18"},{"type":"expectedGoals","value":"0.0299"},{"type":"expectedGoalsNonpenalty","value":"0.0299"},{"type":"expectedGoalsOpenplay","value":"0.0299"},{"type":"expectedGoalsLf","value":"0.0299"},{"type":"expectedGoalsConceded","value":"0.585864"},{"type":"expectedGoalsNonpenaltyConceded","value":"0.585864"},{"type":"expectedGoalsontargetConceded","value":"0.2484"},{"type":"expectedGoalsontargetNonpenaltyConceded","value":"0.2484"},{"type":"expectedAssists","value":"0.00878729"},{"type":"expectedAssistsOpenplay","value":"0.00878729"}]},{"playerId":"1he0x583esqw1ka0ybc2nlz9x","opPlayerId":"166552","firstName":"Nabil","lastName":"Fekir","matchName":"N. Fekir","shirtNumber":18,"position":"Substitute","stat":[{"type":"minsPlayed","value":"10"},{"type":"totalSubOn","value":"1"},{"type":"touches","value":"3"},{"type":"expectedAssists","value":"0.0054382"},{"type":"expectedAssistsOpenplay","value":"0.0054382"}]},{"playerId":"1qywnx1icmb4x7dbhhsck0vrp","opPlayerId":"129479","firstName":"Presnel","lastName":"Kimpembe","matchName":"P. Kimpembe","shirtNumber":3,"position":"Substitute","stat":[]},{"playerId":"6wfwy94p5bm0zv3aku0urfq39","opPlayerId":"86873","firstName":"Benjamin","lastName":"Lecomte","matchName":"B. Lecomte","shirtNumber":1,"position":"Substitute","stat":[]},{"playerId":"ejcyvgclry4g5pc2rtptifphx","opPlayerId":"167449","firstName":"Thomas","lastName":"Lemar","matchName":"T. Lemar","shirtNumber":8,"position":"Substitute","stat":[]},{"playerId":"9q1pgu6p4wcn9qg4idxsipql1","opPlayerId":"102826","firstName":"Benjamin","lastName":"Mendy","matchName":"B. Mendy","shirtNumber":22,"position":"Substitute","stat":[]},{"playerId":"9puzo3psqfjufujh4lo3cug2d","opPlayerId":"49323","firstName":"Steven N'Kemboanza Mike Christopher","lastName":"N'Zonzi","matchName":"S. N'Zonzi","shirtNumber":15,"position":"Substitute","stat":[]},{"playerId":"2smai2vq1r9xnemihvcq0doet","opPlayerId":"41795","firstName":"Adil","lastName":"Rami","matchName":"A. Rami","shirtNumber":17,"position":"Substitute","stat":[]},{"playerId":"2liyw2r4k4gwdkdz51ohws9ud","opPlayerId":"102747","firstName":"Djibril","lastName":"Sidibé","matchName":"D. Sidibé","shirtNumber":19,"position":"Substitute","stat":[]},{"playerId":"8shwa0k28rt5duyrhuqza1hhx","opPlayerId":"95434","firstName":"Florian","lastName":"Thauvin","matchName":"F. Thauvin","shirtNumber":20,"position":"Substitute","stat":[]},{"playerId":"d68byfvk16giaur32gqwpwded","opPlayerId":"168568","firstName":"Corentin","lastName":"Tolisso","matchName":"C. Tolisso","shirtNumber":12,"position":"Substitute","stat":[{"type":"minsPlayed","value":"4"},{"type":"totalSubOn","value":"1"},{"type":"touches","value":"6"},{"type":"expectedAssists","value":"0.0001392"},{"type":"expectedAssistsSetplay","value":"0.00013097"},{"type":"expectedAssistsOpenplay","value":"8.23e-06"}]}],"stat":[{"fh":"1","sh":"1","type":"attBxCentre","value":"2"},{"fh":"1","sh":"3","type":"attObxCentre","value":"4"},{"fh":"0","sh":"1","type":"attFastbreak","value":"1"},{"fh":"1","sh":"0","type":"attFreekickTarget","value":"1"},{"fh":"1","sh":"0","type":"attFreekickTotal","value":"1"},{"fh":"0","sh":"1","type":"attHdMiss","value":"1"},{"fh":"1","sh":"0","type":"attHdTarget","value":"1"},{"fh":"1","sh":"1","type":"attHdTotal","value":"2"},{"fh":"1","sh":"1","type":"attIboxMiss","value":"2"},{"fh":"1","sh":"1","type":"attIboxTarget","value":"2"},{"fh":"0","sh":"2","type":"attLfTarget","value":"2"},{"fh":"0","sh":"3","type":"attLfTotal","value":"3"},{"fh":"1","sh":"1","type":"attMissLeft","value":"2"},{"fh":"0","sh":"1","type":"attMissRight","value":"1"},{"fh":"0","sh":"1","type":"attOboxBlocked","value":"1"},{"fh":"0","sh":"1","type":"attOboxMiss","value":"1"},{"fh":"1","sh":"1","type":"attOboxTarget","value":"2"},{"fh":"2","sh":"4","type":"attOpenplay","value":"6"},{"fh":"1","sh":"0","type":"attRfTarget","value":"1"},{"fh":"2","sh":"1","type":"attRfTotal","value":"3"},{"fh":"1","sh":"0","type":"attSvHighLeft","value":"1"},{"fh":"1","sh":"2","type":"attSvLowRight","value":"3"},{"fh":"0","sh":"1","type":"blockedScoringAtt","value":"1"},{"fh":"1","sh":"2","type":"offtargetAttAssist","value":"3"},{"fh":"1","sh":"2","type":"ontargetAttAssist","value":"3"},{"fh":"2","sh":"2","type":"ontargetScoringAtt","value":"4"},{"fh":"1","sh":"2","type":"shotOffTarget","value":"3"},{"fh":"0","sh":"3","type":"subsMade","value":"3"},{"fh":"2","sh":"4","type":"totalAttAssist","value":"6"},{"fh":"3","sh":"5","type":"totalScoringAtt","value":"8"},{"fh":"294","sh":"300","type":"touches","value":"594"},{"fh":"2","sh":"3","type":"attAssistOpenplay","value":"5"},{"fh":"0","sh":"1","type":"attAssistSetplay","value":"1"},{"fh":"0","sh":"1","type":"shotFastbreak","value":"1"},{"fh":"4","sh":"4","type":"touchesInOppBox","value":"8"},{"fh":"0.4864","sh":"0.2435","type":"expectedGoals","value":"0.7299"},{"fh":"0.4864","sh":"0.2435","type":"expectedGoalsNonpenalty","value":"0.7299"},{"fh":"0.4357","sh":"0.167","type":"expectedGoalsOpenplay","value":"0.6027"},{"fh":"0.0507","sh":"0.0765","type":"expectedGoalsSetplay","value":"0.1272"},{"fh":"0.0543","sh":"0.0765","type":"expectedGoalsHd","value":"0.1308"},{"fh":"0","sh":"0.1072","type":"expectedGoalsLf","value":"0.1072"},{"fh":"0.4321","sh":"0.0598","type":"expectedGoalsRf","value":"0.4919"},{"fh":"0.0507","sh":"0","type":"expectedGoalsFreekick","value":"0.0507"},{"fh":"0.1467","sh":"0.697364","type":"expectedGoalsConceded","value":"0.844064"},{"fh":"0.1467","sh":"0.697364","type":"expectedGoalsNonpenaltyConceded","value":"0.844064"},{"fh":"0.5263","sh":"0.1278","type":"expectedGoalsontarget","value":"0.6541"},{"fh":"0.5263","sh":"0.1278","type":"expectedGoalsontargetNonpenalty","value":"0.6541"},{"fh":"0.2624","sh":"0","type":"expectedGoalsontargetFreekick","value":"0.2624"},{"fh":"0.0248","sh":"0.5587","type":"expectedGoalsontargetConceded","value":"0.5835"},{"fh":"0.0248","sh":"0.5587","type":"expectedGoalsontargetNonpenaltyConceded","value":"0.5835"},{"fh":"0.632471","sh":"0.254122","type":"expectedAssists","value":"0.886593"},{"fh":"0.00165213","sh":"0.0599227","type":"expectedAssistsSetplay","value":"0.0615748"},{"fh":"0.630819","sh":"0.194199","type":"expectedAssistsOpenplay","value":"0.825018"}],"contestantId":"4pz87gsel7183b7kcadw1dwzv","opContestantId":"368","teamOfficial":{"id":"qogjyv8dbeuh4nhoaqfcnc2d","opId":"132","firstName":"Didier","lastName":"Deschamps","type":"manager"}}],"event":[{"id":1848574055,"eventId":189,"typeId":15,"periodId":1,"timeMin":17,"timeSec":43,"contestantId":"3l2t2db0c5ow2f7s7bhr6mij4","opContestantId":"357","playerName":"T. Werner","opPlayerId":"165153","playerId":"2pjr6yz65f4uqvwniy4vphn85","outcome":1,"x":87.2,"y":71.3,"timeStamp":"2018-09-06T19:05:06.296","lastModified":"2018-09-07T08:43:55","assist":1,"qualifier":[{"id":1098244792,"qualifierId":29},{"id":1208456364,"qualifierId":326,"value":"3"},{"id":1218214306,"qualifierId":147,"value":"53.6"},{"id":1468787471,"qualifierId":22},{"id":1519165478,"qualifierId":103,"value":"4.4"},{"id":1549729692,"qualifierId":20},{"id":1553944967,"qualifierId":102,"value":"49.7"},{"id":1704702993,"qualifierId":215},{"id":1749665785,"qualifierId":322,"value":"0.0248"},{"id":1752387294,"qualifierId":233,"value":"141"},{"id":1772283626,"qualifierId":321,"value":"0.0414"},{"id":1786093665,"qualifierId":146,"value":"97.8"},{"id":1953205018,"qualifierId":327,"value":"2"},{"id":2009380342,"qualifierId":64},{"id":2097496812,"qualifierId":78},{"id":2107778685,"qualifierId":56,"value":"Center"}]},{"id":1753769060,"eventId":369,"typeId":13,"periodId":1,"timeMin":34,"timeSec":9,"contestantId":"3l2t2db0c5ow2f7s7bhr6mij4","opContestantId":"357","playerName":"A. Rüdiger","opPlayerId":"102380","playerId":"6fzbp94hf19ysotdassrqdc5x","outcome":1,"x":89.9,"y":48.5,"timeStamp":"2018-09-06T19:21:32.292","lastModified":"2018-09-07T09:23:23","assist":1,"qualifier":[{"id":1138848042,"qualifierId":73},{"id":1185662158,"qualifierId":25},{"id":1227974048,"qualifierId":102,"value":"74.3"},{"id":1332997264,"qualifierId":326,"value":"3"},{"id":1469766490,"qualifierId":29},{"id":1518705493,"qualifierId":146,"value":"95.0"},{"id":1528843116,"qualifierId":17},{"id":1675145035,"qualifierId":154},{"id":1722279077,"qualifierId":321,"value":"0.052"},{"id":1784168023,"qualifierId":327,"value":"2"},{"id":1876958547,"qualifierId":153},{"id":1934056929,"qualifierId":328},{"id":1960296118,"qualifierId":147,"value":"62.5"},{"id":1972191706,"qualifierId":56,"value":"Center"},{"id":2016098505,"qualifierId":103,"value":"29.2"},{"id":2087227188,"qualifierId":15}]},{"id":1234038255,"eventId":370,"typeId":13,"periodId":1,"timeMin":34,"timeSec":10,"contestantId":"3l2t2db0c5ow2f7s7bhr6mij4","opContestantId":"357","playerName":"M. Hummels","opPlayerId":"38392","playerId":"cd6i7khi5wgsfsg19c9tcjydx","outcome":1,"x":95.3,"y":61.2,"timeStamp":"2018-09-06T19:21:33.292","lastModified":"2018-09-07T09:23:58","assist":1,"qualifier":[{"id":1094204338,"qualifierId":102,"value":"60.2"},{"id":1167057197,"qualifierId":29},{"id":1167712289,"qualifierId":15},{"id":1183320470,"qualifierId":327,"value":"1"},{"id":1307559277,"qualifierId":103,"value":"61.1"},{"id":1566683220,"qualifierId":321,"value":"0.0533"},{"id":1601086658,"qualifierId":231,"value":"56.0"},{"id":1705743465,"qualifierId":77},{"id":1809144320,"qualifierId":328},{"id":1869394358,"qualifierId":326,"value":"1"},{"id":1899837285,"qualifierId":61},{"id":1930612072,"qualifierId":25},{"id":2040660357,"qualifierId":56,"value":"Center"},{"id":2142235940,"qualifierId":230,"value":"98.9"}]},{"id":1963562138,"eventId":275,"typeId":15,"periodId":1,"timeMin":35,"timeSec":45,"contestantId":"4pz87gsel7183b7kcadw1dwzv","opContestantId":"368","playerName":"O. Giroud","opPlayerId":"44346","playerId":"5awkzgwwh48prwgvxwewuc5hx","outcome":1,"x":89.9,"y":45,"timeStamp":"2018-09-06T19:23:08.654","lastModified":"2018-09-07T09:27:36","assist":1,"qualifier":[{"id":1107123941,"qualifierId":327,"value":"2"},{"id":1118018826,"qualifierId":29},{"id":1129142276,"qualifierId":15},{"id":1229053233,"qualifierId":328},{"id":1310563505,"qualifierId":56,"value":"Center"},{"id":1327456581,"qualifierId":322,"value":"0.2639"},{"id":1379172846,"qualifierId":154},{"id":1427949303,"qualifierId":321,"value":"0.0543"},{"id":1489032053,"qualifierId":147,"value":"47.8"},{"id":1495296834,"qualifierId":17},{"id":1570717123,"qualifierId":102,"value":"45.6"},{"id":1694477058,"qualifierId":103,"value":"12.0"},{"id":1851598580,"qualifierId":22},{"id":1906049149,"qualifierId":326,"value":"3"},{"id":1952016970,"qualifierId":233,"value":"377"},{"id":1988564690,"qualifierId":146,"value":"99.0"},{"id":2139957374,"qualifierId":80}]},{"id":1469108250,"eventId":339,"typeId":15,"periodId":1,"timeMin":42,"timeSec":17,"contestantId":"4pz87gsel7183b7kcadw1dwzv","opContestantId":"368","playerName":"K. Mbappé","opPlayerId":"220160","playerId":"5e9ilgrz3tzg9kd1gk3yvrahh","outcome":1,"x":74,"y":70,"timeStamp":"2018-09-06T19:29:41.340","lastModified":"2018-09-07T09:42:35","qualifier":[{"id":1087973786,"qualifierId":103,"value":"34.8"},{"id":1102429400,"qualifierId":146,"value":"99.1"},{"id":1116746672,"qualifierId":18},{"id":1161003457,"qualifierId":322,"value":"0.2624"},{"id":1313552333,"qualifierId":102,"value":"52.5"},{"id":1486810481,"qualifierId":77},{"id":1500152594,"qualifierId":20},{"id":1513029279,"qualifierId":56,"value":"Center"},{"id":1598803499,"qualifierId":321,"value":"0.0507"},{"id":1641618423,"qualifierId":233,"value":"432"},{"id":1701663523,"qualifierId":26},{"id":1755012953,"qualifierId":327,"value":"3"},{"id":1758471526,"qualifierId":120},{"id":1896176974,"qualifierId":326,"value":"1"},{"id":1932600390,"qualifierId":147,"value":"48.4"}]},{"id":1688164615,"eventId":387,"typeId":13,"periodId":1,"timeMin":45,"timeSec":46,"contestantId":"4pz87gsel7183b7kcadw1dwzv","opContestantId":"368","playerName":"O. Giroud","opPlayerId":"44346","playerId":"5awkzgwwh48prwgvxwewuc5hx","outcome":1,"x":97,"y":46.6,"timeStamp":"2018-09-06T19:33:09.780","lastModified":"2018-09-07T09:54:55","assist":1,"qualifier":[{"id":1092230377,"qualifierId":326,"value":"3"},{"id":1114199164,"qualifierId":29},{"id":1197312595,"qualifierId":230,"value":"99.4"},{"id":1286883687,"qualifierId":328},{"id":1347556831,"qualifierId":103,"value":"2.8"},{"id":1499169479,"qualifierId":73},{"id":1502915096,"qualifierId":327,"value":"2"},{"id":1581230508,"qualifierId":22},{"id":1591468776,"qualifierId":231,"value":"46.2"},{"id":1664343711,"qualifierId":20},{"id":1814161021,"qualifierId":16},{"id":2018785278,"qualifierId":154},{"id":2033973336,"qualifierId":102,"value":"67.9"},{"id":2041034880,"qualifierId":56,"value":"Center"},{"id":2098261335,"qualifierId":321,"value":"0.3814"}]},{"id":2105007143,"eventId":433,"typeId":15,"periodId":2,"timeMin":48,"timeSec":47,"contestantId":"4pz87gsel7183b7kcadw1dwzv","opContestantId":"368","playerName":"A. Griezmann","opPlayerId":"76650","playerId":"716n1970vi9rvw5b4w9qmjfth","outcome":1,"x":86.8,"y":33.8,"timeStamp":"2018-09-06T19:54:29.402","lastModified":"2018-09-07T10:17:43","assist":1,"qualifier":[{"id":1126827821,"qualifierId":80},{"id":1140187534,"qualifierId":72},{"id":1162100536,"qualifierId":103,"value":"8.2"},{"id":1191571530,"qualifierId":327,"value":"2"},{"id":1239030932,"qualifierId":146,"value":"98.6"},{"id":1354438126,"qualifierId":215},{"id":1430419961,"qualifierId":22},{"id":1506832212,"qualifierId":322,"value":"0.0582"},{"id":1554464390,"qualifierId":29},{"id":1657685959,"qualifierId":321,"value":"0.0482"},{"id":1756983767,"qualifierId":63},{"id":1826763277,"qualifierId":102,"value":"48.0"},{"id":1917175867,"qualifierId":326,"value":"1"},{"id":1934453505,"qualifierId":233,"value":"524"},{"id":1999161302,"qualifierId":56,"value":"Center"},{"id":2023368630,"qualifierId":147,"value":"47.3"}]},{"id":1977012927,"eventId":648,"typeId":15,"periodId":2,"timeMin":60,"timeSec":51,"contestantId":"3l2t2db0c5ow2f7s7bhr6mij4","opContestantId":"357","playerName":"T. Müller","opPlayerId":"55634","playerId":"4fq74wp7xzwm214veuxqpdz9x","outcome":1,"x":73.1,"y":65.7,"timeStamp":"2018-09-06T20:06:33.156","lastModified":"2018-09-07T10:52:41","assist":1,"qualifier":[{"id":1085674182,"qualifierId":327,"value":"2"},{"id":1142346301,"qualifierId":147,"value":"50.5"},{"id":1187043358,"qualifierId":20},{"id":1202254585,"qualifierId":233,"value":"528"},{"id":1285148722,"qualifierId":18},{"id":1303512816,"qualifierId":103,"value":"1.9"},{"id":1343767609,"qualifierId":56,"value":"Center"},{"id":1613662560,"qualifierId":22},{"id":1741216953,"qualifierId":29},{"id":1795683662,"qualifierId":76},{"id":1814615874,"qualifierId":326,"value":"1"},{"id":1820141428,"qualifierId":322,"value":"0.1724"},{"id":1844391119,"qualifierId":321,"value":"0.027"},{"id":1868508781,"qualifierId":102,"value":"53.1"},{"id":1870616588,"qualifierId":146,"value":"99.5"},{"id":1877671726,"qualifierId":114},{"id":2131350708,"qualifierId":215}]},{"id":2073016915,"eventId":660,"typeId":13,"periodId":2,"timeMin":61,"timeSec":58,"contestantId":"3l2t2db0c5ow2f7s7bhr6mij4","opContestantId":"357","playerName":"J. Kimmich","opPlayerId":"165687","playerId":"97nv3y9z2ajz6b4ynoo0jn3kl","outcome":1,"x":69.5,"y":51.9,"timeStamp":"2018-09-06T20:07:39.676","lastModified":"2018-09-07T10:55:52","assist":1,"qualifier":[{"id":1156681939,"qualifierId":29},{"id":1162925911,"qualifierId":326,"value":"1"},{"id":1184504079,"qualifierId":20},{"id":1210806892,"qualifierId":321,"value":"0.0256"},{"id":1224892729,"qualifierId":231,"value":"48.6"},{"id":1354774883,"qualifierId":18},{"id":1621942546,"qualifierId":102,"value":"49.2"},{"id":1682751156,"qualifierId":215},{"id":1722181038,"qualifierId":22},{"id":1731297228,"qualifierId":74},{"id":1840971511,"qualifierId":230,"value":"98.2"},{"id":1867977510,"qualifierId":103,"value":"70.8"},{"id":1952700658,"qualifierId":327,"value":"2"},{"id":2056236229,"qualifierId":56,"value":"Center"}]},{"id":1351642088,"eventId":563,"typeId":15,"periodId":2,"timeMin":63,"timeSec":25,"contestantId":"4pz87gsel7183b7kcadw1dwzv","opContestantId":"368","playerName":"A. Griezmann","opPlayerId":"76650","playerId":"716n1970vi9rvw5b4w9qmjfth","outcome":1,"x":72.9,"y":53.8,"timeStamp":"2018-09-06T20:09:07.309","lastModified":"2018-09-07T11:02:30","qualifier":[{"id":1234911843,"qualifierId":72},{"id":1339905417,"qualifierId":321,"value":"0.0291"},{"id":1404866909,"qualifierId":146,"value":"99.0"},{"id":1437368152,"qualifierId":322,"value":"0.0696"},{"id":1568565184,"qualifierId":233,"value":"669"},{"id":1668610461,"qualifierId":22},{"id":1693121134,"qualifierId":103,"value":"14.6"},{"id":1767552686,"qualifierId":18},{"id":1780566923,"qualifierId":147,"value":"51.6"},{"id":1785341823,"qualifierId":326,"value":"1"},{"id":1819839136,"qualifierId":56,"value":"Center"},{"id":1948451481,"qualifierId":215},{"id":2024238839,"qualifierId":327,"value":"2"},{"id":2089013969,"qualifierId":102,"value":"47.9"},{"id":2141691730,"qualifierId":80}]},{"id":1294149691,"eventId":682,"typeId":15,"periodId":2,"timeMin":63,"timeSec":55,"contestantId":"3l2t2db0c5ow2f7s7bhr6mij4","opContestantId":"357","playerName":"M. Reus","opPlayerId":"50523","playerId":"btzfq6521zl3q5uqus8ltov6d","outcome":1,"x":83.1,"y":49.4,"timeStamp":"2018-09-06T20:09:37.450","lastModified":"2018-09-07T11:05:15","assist":1,"qualifier":[{"id":1159292600,"qualifierId":322,"value":"0.1379"},{"id":1274530762,"qualifierId":22},{"id":1324942539,"qualifierId":326,"value":"2"},{"id":1345559203,"qualifierId":328},{"id":1427398965,"qualifierId":56,"value":"Center"},{"id":1432234564,"qualifierId":147,"value":"47.3"},{"id":1492979510,"qualifierId":17},{"id":1531622987,"qualifierId":102,"value":"51.9"},{"id":1585803002,"qualifierId":154},{"id":1709906529,"qualifierId":20},{"id":1743668583,"qualifierId":103,"value":"24.7"},{"id":1795975162,"qualifierId":29},{"id":1818137158,"qualifierId":327,"value":"1"},{"id":1850077204,"qualifierId":321,"value":"0.0589"},{"id":1910985248,"qualifierId":146,"value":"98.5"},{"id":1976367055,"qualifierId":233,"value":"566"},{"id":2062947657,"qualifierId":77}]},{"id":2110430855,"eventId":606,"typeId":13,"periodId":2,"timeMin":68,"timeSec":30,"contestantId":"4pz87gsel7183b7kcadw1dwzv","opContestantId":"368","playerName":"K. Mbappé","opPlayerId":"220160","playerId":"5e9ilgrz3tzg9kd1gk3yvrahh","outcome":1,"x":80.3,"y":30.4,"timeStamp":"2018-09-06T20:14:12.374","lastModified":"2018-09-07T11:19:59","assist":1,"qualifier":[{"id":1097757912,"qualifierId":326,"value":"2"},{"id":1162201092,"qualifierId":215},{"id":1185771233,"qualifierId":73},{"id":1269673795,"qualifierId":231,"value":"48.6"},{"id":1333984673,"qualifierId":29},{"id":1373595635,"qualifierId":230,"value":"95.8"},{"id":1535659764,"qualifierId":20},{"id":1543019050,"qualifierId":23},{"id":1719889049,"qualifierId":56,"value":"Center"},{"id":1935037709,"qualifierId":321,"value":"0.0598"},{"id":1952344629,"qualifierId":327,"value":"1"},{"id":2100147431,"qualifierId":102,"value":"65.4"},{"id":2107430738,"qualifierId":18},{"id":2138318316,"qualifierId":103,"value":"4.2"}]},{"id":1115535112,"eventId":782,"typeId":15,"periodId":2,"timeMin":71,"timeSec":17,"contestantId":"3l2t2db0c5ow2f7s7bhr6mij4","opContestantId":"357","playerName":"T. Müller","opPlayerId":"55634","playerId":"4fq74wp7xzwm214veuxqpdz9x","outcome":1,"x":87.8,"y":46.4,"timeStamp":"2018-09-06T20:16:59.202","lastModified":"2018-09-07T11:27:17","assist":1,"qualifier":[{"id":1169523720,"qualifierId":233,"value":"632"},{"id":1284190561,"qualifierId":23},{"id":1399242708,"qualifierId":147,"value":"47.1"},{"id":1462251522,"qualifierId":17},{"id":1480086983,"qualifierId":20},{"id":1486078715,"qualifierId":321,"value":"0.1466"},{"id":1488442696,"qualifierId":82},{"id":1502197141,"qualifierId":326,"value":"3"},{"id":1751273857,"qualifierId":29},{"id":1830652460,"qualifierId":56,"value":"Center"},{"id":1869075227,"qualifierId":108},{"id":1895507905,"qualifierId":327,"value":"2"},{"id":1908316054,"qualifierId":146,"value":"89.8"},{"id":2061142846,"qualifierId":215},{"id":2123837661,"qualifierId":154}]},{"id":1195886784,"eventId":783,"typeId":15,"periodId":2,"timeMin":71,"timeSec":19,"contestantId":"3l2t2db0c5ow2f7s7bhr6mij4","opContestantId":"357","playerName":"M. Hummels","opPlayerId":"38392","playerId":"cd6i7khi5wgsfsg19c9tcjydx","outcome":1,"x":89.5,"y":67.2,"timeStamp":"2018-09-06T20:17:01.362","lastModified":"2018-09-07T11:27:51","qualifier":[{"id":1079643928,"qualifierId":322,"value":"0.0319"},{"id":1116923824,"qualifierId":146,"value":"98.4"},{"id":1143087862,"qualifierId":120},{"id":1204095588,"qualifierId":327,"value":"1"},{"id":1230373176,"qualifierId":147,"value":"52.0"},{"id":1291082254,"qualifierId":338,"value":"782"},{"id":1410788244,"qualifierId":326,"value":"1"},{"id":1557199888,"qualifierId":102,"value":"49.6"},{"id":1663059506,"qualifierId":78},{"id":1716750361,"qualifierId":103,"value":"10.1"},{"id":1724503575,"qualifierId":328},{"id":1800941252,"qualifierId":20},{"id":1807517186,"qualifierId":64},{"id":1845871539,"qualifierId":23},{"id":1919677065,"qualifierId":56,"value":"Center"},{"id":1998419929,"qualifierId":233,"value":"633"},{"id":2000597191,"qualifierId":323},{"id":2054121880,"qualifierId":321,"value":"0.1059"}]},{"id":1814580877,"eventId":784,"typeId":13,"periodId":2,"timeMin":71,"timeSec":21,"contestantId":"3l2t2db0c5ow2f7s7bhr6mij4","opContestantId":"357","playerName":"T. Müller","opPlayerId":"55634","playerId":"4fq74wp7xzwm214veuxqpdz9x","outcome":1,"x":87.2,"y":47,"timeStamp":"2018-09-06T20:17:02.471","lastModified":"2018-09-07T11:28:17","qualifier":[{"id":1094681091,"qualifierId":231,"value":"50.5"},{"id":1099687707,"qualifierId":323},{"id":1146569734,"qualifierId":326,"value":"2"},{"id":1197706392,"qualifierId":56,"value":"Center"},{"id":1429239140,"qualifierId":230,"value":"97.8"},{"id":1452775217,"qualifierId":321,"value":"0.1393"},{"id":1473311372,"qualifierId":23},{"id":1484436034,"qualifierId":81},{"id":1590937107,"qualifierId":103,"value":"86.1"},{"id":1590973343,"qualifierId":108},{"id":1703590041,"qualifierId":338,"value":"783"},{"id":1769319080,"qualifierId":20},{"id":1835785018,"qualifierId":17},{"id":1853900085,"qualifierId":327,"value":"2"},{"id":1900396782,"qualifierId":215},{"id":1979043017,"qualifierId":102,"value":"42.0"},{"id":2147285236,"qualifierId":328}]},{"id":1512185256,"eventId":799,"typeId":13,"periodId":2,"timeMin":72,"timeSec":44,"contestantId":"3l2t2db0c5ow2f7s7bhr6mij4","opContestantId":"357","playerName":"İ. Gündoğan","opPlayerId":"59859","playerId":"9wbf00lybk9fqablaqwg5cn2t","outcome":1,"x":76.1,"y":53.2,"timeStamp":"2018-09-06T20:18:25.682","lastModified":"2018-09-07T11:32:15","assist":1,"qualifier":[{"id":1077687742,"qualifierId":321,"value":"0.0336"},{"id":1147366714,"qualifierId":215},{"id":1148365115,"qualifierId":326,"value":"3"},{"id":1176426472,"qualifierId":56,"value":"Center"},{"id":1181681583,"qualifierId":327,"value":"2"},{"id":1237269391,"qualifierId":20},{"id":1247110889,"qualifierId":231,"value":"47.3"},{"id":1744386850,"qualifierId":18},{"id":1841731967,"qualifierId":230,"value":"98.5"},{"id":1856432501,"qualifierId":29},{"id":1869249408,"qualifierId":22},{"id":1915182406,"qualifierId":102,"value":"40.2"},{"id":1968549804,"qualifierId":81},{"id":2038529772,"qualifierId":103,"value":"55.6"}]},{"id":1593570566,"eventId":835,"typeId":15,"periodId":2,"timeMin":74,"timeSec":37,"contestantId":"3l2t2db0c5ow2f7s7bhr6mij4","opContestantId":"357","playerName":"M. Ginter","opPlayerId":"111251","playerId":"84mp3eqt1ckw107hwxpby9cd1","outcome":1,"x":92.5,"y":45.8,"timeStamp":"2018-09-06T20:20:18.371","lastModified":"2018-09-07T12:14:43","assist":1,"qualifier":[{"id":1136624224,"qualifierId":147,"value":"49.5"},{"id":1157471015,"qualifierId":326,"value":"3"},{"id":1377381989,"qualifierId":103,"value":"13.3"},{"id":1397213123,"qualifierId":76},{"id":1585938636,"qualifierId":25},{"id":1602209970,"qualifierId":233,"value":"644"},{"id":1602378570,"qualifierId":321,"value":"0.0712"},{"id":1653361557,"qualifierId":29},{"id":1732364116,"qualifierId":15},{"id":1810387142,"qualifierId":322,"value":"0.1577"},{"id":1811948478,"qualifierId":146,"value":"99.4"},{"id":1881701984,"qualifierId":154},{"id":1918011102,"qualifierId":17},{"id":1947239733,"qualifierId":102,"value":"52.7"},{"id":1973272817,"qualifierId":327,"value":"2"},{"id":2042475047,"qualifierId":328},{"id":2062196455,"qualifierId":56,"value":"Center"}]},{"id":1294980763,"eventId":839,"typeId":15,"periodId":2,"timeMin":75,"timeSec":9,"contestantId":"3l2t2db0c5ow2f7s7bhr6mij4","opContestantId":"357","playerName":"M. Hummels","opPlayerId":"38392","playerId":"cd6i7khi5wgsfsg19c9tcjydx","outcome":1,"x":93.7,"y":57.3,"timeStamp":"2018-09-06T20:20:50.371","lastModified":"2018-09-07T12:14:43","assist":1,"qualifier":[{"id":1097385712,"qualifierId":322,"value":"0.0588"},{"id":1178082589,"qualifierId":15},{"id":1286326577,"qualifierId":56,"value":"Center"},{"id":1318621109,"qualifierId":233,"value":"647"},{"id":1355178842,"qualifierId":146,"value":"98.5"},{"id":1392923778,"qualifierId":327,"value":"2"},{"id":1419652045,"qualifierId":25},{"id":1438560709,"qualifierId":147,"value":"52.3"},{"id":1443210126,"qualifierId":17},{"id":1595169903,"qualifierId":321,"value":"0.0684"},{"id":1657042657,"qualifierId":328},{"id":1665777206,"qualifierId":102,"value":"50.6"},{"id":1892262018,"qualifierId":79},{"id":1924836264,"qualifierId":326,"value":"3"},{"id":2075388348,"qualifierId":29},{"id":2125915446,"qualifierId":103,"value":"27.2"},{"id":2140714733,"qualifierId":154}]},{"id":1768051110,"eventId":856,"typeId":15,"periodId":2,"timeMin":76,"timeSec":38,"contestantId":"3l2t2db0c5ow2f7s7bhr6mij4","opContestantId":"357","playerName":"İ. Gündoğan","opPlayerId":"59859","playerId":"9wbf00lybk9fqablaqwg5cn2t","outcome":1,"x":90.3,"y":62,"timeStamp":"2018-09-06T20:22:19.629","lastModified":"2018-09-07T11:45:26","qualifier":[{"id":1221599265,"qualifierId":327,"value":"2"},{"id":1387800516,"qualifierId":321,"value":"0.0694"},{"id":1523451230,"qualifierId":56,"value":"Center"},{"id":1697476742,"qualifierId":326,"value":"3"},{"id":1698828078,"qualifierId":146,"value":"93.0"},{"id":1814084824,"qualifierId":147,"value":"58.8"},{"id":1825452370,"qualifierId":82},{"id":1831840807,"qualifierId":17},{"id":1918857749,"qualifierId":328},{"id":1956349959,"qualifierId":233,"value":"661"},{"id":1972274648,"qualifierId":22},{"id":1976141211,"qualifierId":72}]},{"id":1921543675,"eventId":703,"typeId":13,"periodId":2,"timeMin":82,"timeSec":7,"contestantId":"4pz87gsel7183b7kcadw1dwzv","opContestantId":"368","playerName":"P. Pogba","opPlayerId":"74208","playerId":"f482w50k80zbyb2ykh84yijf9","outcome":1,"x":93,"y":45.6,"timeStamp":"2018-09-06T20:27:48.471","lastModified":"2018-09-07T11:56:24","assist":1,"qualifier":[{"id":1084885659,"qualifierId":321,"value":"0.0765"},{"id":1088013309,"qualifierId":146,"value":"99.0"},{"id":1139899460,"qualifierId":56,"value":"Center"},{"id":1284233232,"qualifierId":103,"value":"27.8"},{"id":1307139768,"qualifierId":326,"value":"3"},{"id":1346640075,"qualifierId":328},{"id":1362641070,"qualifierId":29},{"id":1529507504,"qualifierId":25},{"id":1723825363,"qualifierId":17},{"id":1744242085,"qualifierId":327,"value":"2"},{"id":1852834432,"qualifierId":154},{"id":1923143861,"qualifierId":147,"value":"31.2"},{"id":1933142468,"qualifierId":75},{"id":2052161204,"qualifierId":15},{"id":2061784196,"qualifierId":102,"value":"33.3"},{"id":2099847247,"qualifierId":153}]},{"id":1782608285,"eventId":765,"typeId":15,"periodId":2,"timeMin":90,"timeSec":52,"contestantId":"4pz87gsel7183b7kcadw1dwzv","opContestantId":"368","playerName":"O. Dembélé","opPlayerId":"219438","playerId":"ckaqxlw257qzj8vjdumvwbaad","outcome":1,"x":73.6,"y":54.2,"timeStamp":"2018-09-06T20:36:34.304","lastModified":"2018-09-07T12:17:46","assist":1,"qualifier":[{"id":1109069196,"qualifierId":326,"value":"1"},{"id":1143636481,"qualifierId":146,"value":"78.5"},{"id":1210755993,"qualifierId":56,"value":"Center"},{"id":1381180906,"qualifierId":147,"value":"53.6"},{"id":1444850058,"qualifierId":114},{"id":1484052507,"qualifierId":72},{"id":1522868985,"qualifierId":29},{"id":1614506108,"qualifierId":321,"value":"0.0299"},{"id":1618997750,"qualifierId":215},{"id":1700728628,"qualifierId":82},{"id":1730312141,"qualifierId":22},{"id":1849100382,"qualifierId":233,"value":"1016"},{"id":2038264349,"qualifierId":18},{"id":2142148086,"qualifierId":327,"value":"2"}]}]}}